pypdfeditor_core/__init__.py
pypdfeditor_core/__main__.py
pypdfeditor_core/application.py
pypdfeditor_core/functions.py
pypdfeditor_core/language.py
pypdfeditor_core/style_sheets.py
pypdfeditor_core/window_effect.py
pypdfeditor_core/windows.py
pypdfeditor_core/icons/Add.svg
pypdfeditor_core/icons/Add_h.svg
pypdfeditor_core/icons/Add_p.svg
pypdfeditor_core/icons/Photo.svg
pypdfeditor_core/icons/__init__.py
pypdfeditor_core/icons/arrow_move.svg
pypdfeditor_core/icons/book2.svg
pypdfeditor_core/icons/chevron_down.svg
pypdfeditor_core/icons/color.svg
pypdfeditor_core/icons/color_h.svg
pypdfeditor_core/icons/color_p.svg
pypdfeditor_core/icons/delete.svg
pypdfeditor_core/icons/delete_h.svg
pypdfeditor_core/icons/delete_p.svg
pypdfeditor_core/icons/dismiss.svg
pypdfeditor_core/icons/dismiss_h.svg
pypdfeditor_core/icons/down.svg
pypdfeditor_core/icons/down_h.svg
pypdfeditor_core/icons/down_p.svg
pypdfeditor_core/icons/edit.svg
pypdfeditor_core/icons/folder.svg
pypdfeditor_core/icons/folder_d.svg
pypdfeditor_core/icons/folder_h.svg
pypdfeditor_core/icons/folder_p.svg
pypdfeditor_core/icons/font.svg
pypdfeditor_core/icons/font_h.svg
pypdfeditor_core/icons/font_p.svg
pypdfeditor_core/icons/home.svg
pypdfeditor_core/icons/lock.svg
pypdfeditor_core/icons/maximize.svg
pypdfeditor_core/icons/merge.svg
pypdfeditor_core/icons/metadata.svg
pypdfeditor_core/icons/minimize.svg
pypdfeditor_core/icons/more.svg
pypdfeditor_core/icons/more_d.svg
pypdfeditor_core/icons/more_h.svg
pypdfeditor_core/icons/more_p.svg
pypdfeditor_core/icons/move_page.svg
pypdfeditor_core/icons/pdf icon.svg
pypdfeditor_core/icons/rotate_anticlockwise.svg
pypdfeditor_core/icons/rotate_clockwise.svg
pypdfeditor_core/icons/settings.svg
pypdfeditor_core/icons/settings_h.svg
pypdfeditor_core/icons/settings_p.svg
pypdfeditor_core/icons/square_multiple.svg
pypdfeditor_core/icons/sync.svg
pypdfeditor_core/icons/sync_h.svg
pypdfeditor_core/icons/sync_p.svg
pypdfeditor_core/icons/view.svg
pypdfeditor_core/icons/view_h.svg
pypdfeditor_gui-3.1.4.dist-info/licenses/LICENSE
pypdfeditor_gui-3.1.4.dist-info/METADATA
pypdfeditor_gui-3.1.4.dist-info/WHEEL
pypdfeditor_gui-3.1.4.dist-info/entry_points.txt
pypdfeditor_gui-3.1.4.dist-info/top_level.txt
pypdfeditor_gui-3.1.4.dist-info/RECORD
