Metadata-Version: 2.4
Name: pyPDFeditor-GUI
Version: 3.1.4
Summary: A desktop application to edit PDF files
Home-page: https://github.com/Augus1999/pyPDFeditor-GUI/
Author: Nianze A. TAO
Author-email: Augus_1999@outlook.com
License: MIT
Project-URL: Source, https://github.com/Augus1999/pyPDFeditor-GUI
Classifier: Development Status :: 5 - Production/Stable
Classifier: Intended Audience :: End Users/Desktop
Classifier: Natural Language :: Chinese (Traditional)
Classifier: Natural Language :: English
Classifier: Natural Language :: Japanese
Classifier: Operating System :: MacOS
Classifier: Operating System :: Microsoft :: Windows
Classifier: Operating System :: POSIX :: Linux
Classifier: Programming Language :: Python :: 3
Classifier: Topic :: Office/Business
Requires-Python: >=3.10
License-File: LICENSE
Requires-Dist: PyMuPDF<1.28.0,>=1.26.5
Requires-Dist: PyQt6>=6.7.0
Dynamic: author
Dynamic: author-email
Dynamic: classifier
Dynamic: description
Dynamic: description-content-type
Dynamic: home-page
Dynamic: license
Dynamic: license-file
Dynamic: project-url
Dynamic: requires-dist
Dynamic: requires-python
Dynamic: summary
